pytest_checkdocs/__init__.py
pytest_checkdocs-2.13.0.dist-info/LICENSE
pytest_checkdocs-2.13.0.dist-info/METADATA
pytest_checkdocs-2.13.0.dist-info/WHEEL
pytest_checkdocs-2.13.0.dist-info/entry_points.txt
pytest_checkdocs-2.13.0.dist-info/top_level.txt
pytest_checkdocs-2.13.0.dist-info/RECORD
